<?xml version="1.0" encoding="UTF-8" standalone="yes"?>




<item>
<title>[COLOR  yellow]* [/COLOR][COLOR yellow]THE[/COLOR][COLOR red]PELICULAS ESPAÑOL[/COLOR][COLOR  lime]* [/COLOR][COLOR  lime] [/COLOR]</title>
<link>$doregex[makelist]</link>
<regex>
  <name>makelist</name>
  <listrepeat><![CDATA[
        <title>[COLOR yellow] [makelist.param3] [/COLOR]</title>
        <link>$doregex[getUrl]</link>
<fanart>http://mundokodi.com/wp-content/uploads/2016/02/pelis-magnet.png?x86522</fanart>
<thumbnail>http://mundokodi.com/wp-content/uploads/2016/02/pelis-magnet.png?x86522</thumbnail>
]]></listrepeat>
<expres><![CDATA[href="\/.*,(.*?),list.*\n.*\n.*\n.*href="\/([^"]*)".*?>(.*?)<]]></expres>
<page>http://diskokosmiko.mx/chinchetas/peliculas-espanol-32573/list,1,1</page>
<cookieJar></cookieJar>
</regex>
<regex>
<name>getUrl</name>
<expres>DownloadUrl":"([^"]+)<expres>
<page>http://diskokosmiko.mx/action/DownloadFile?location=fi&f=[makelist.param1]</page>
<rawpost>fileId=[makelist.param1]&__RequestVerificationToken=$doregex[tok]</rawpost>
<referer>http://diskokosmiko.mx/[makelist.param2]</referer>
<connection>keep-alive</connection>
<accept>*/*</accept>
<X-Req>XMLHttpRequest</X-Req>
<cookieJar></cookieJar>
</regex>
<regex>
<name>tok</name>
<expres>DownloadFile.*RequestVerificationToken.*?value="([^"]+)<expres>
<page>http://diskokosmiko.mx/chinchetas/peliculas-espanol-32573/list,1,2</page>
<referer></referer>
<connection>keep-alive</connection>
<cookieJar></cookieJar>
</regex>
<fanart>http://mundokodi.com/wp-content/uploads/2016/02/pelis-magnet.png</fanart>
<thumbnail>http://mundokodi.com/wp-content/uploads/2016/02/pelis-magnet.png</thumbnail>
</item>
<regex>
<name>tok</name>
<expres>DownloadFile.*RequestVerificationToken.*?value="([^"]+)<expres>
<page>http://diskokosmiko.mx/chinchetas/peliculas-espanol-32573/list,1,3</page>
<referer></referer>
<connection>keep-alive</connection>
<cookieJar></cookieJar>
</regex>
<fanart>http://mundokodi.com/wp-content/uploads/2016/02/pelis-magnet.png</fanart>
<thumbnail>http://mundokodi.com/wp-content/uploads/2016/02/pelis-magnet.png</thumbnail>
</item>
<regex>
<name>tok</name>
<expres>DownloadFile.*RequestVerificationToken.*?value="([^"]+)<expres>
<page>http://diskokosmiko.mx/chinchetas/peliculas-espanol-32573/list,1,4</page>
<referer></referer>
<connection>keep-alive</connection>
<cookieJar></cookieJar>
</regex>
<fanart>http://mundokodi.com/wp-content/uploads/2016/02/pelis-magnet.png</fanart>
<thumbnail>http://mundokodi.com/wp-content/uploads/2016/02/pelis-magnet.png</thumbnail>
</item>
  
<?xml version="1.0" encoding="UTF-8" standalone="yes"?>




<item>
<title>[COLOR  yellow]* [/COLOR][COLOR yellow]THE[/COLOR][COLOR red]peliculas-de-drama[/COLOR][COLOR  lime]* [/COLOR][COLOR  lime] TEMPORADA 1[/COLOR]</title>
<link>$doregex[makelist]</link>
<regex>
  <name>makelist</name>
  <listrepeat><![CDATA[
        <title>[COLOR yellow] [makelist.param3] [/COLOR]</title>
        <link>$doregex[getUrl]</link>
<fanart>http://uscdn02.mundotkm.com/2015/12/peliculas.jpg</fanart>
<thumbnail>http://uscdn02.mundotkm.com/2015/12/peliculas.jpg</thumbnail>
]]></listrepeat>
<expres><![CDATA[href="\/.*,(.*?),list.*\n.*\n.*\n.*href="\/([^"]*)".*?>(.*?)<]]></expres>
<page>http://diskokosmiko.mx/marcos20/peliculas-de-drama-en-espanol-latino-18845/list,1,3</page>
<cookieJar></cookieJar>
</regex>
<regex>
<name>getUrl</name>
<expres>DownloadUrl":"([^"]+)<expres>
<page>http://diskokosmiko.mx/action/DownloadFile?location=fi&f=[makelist.param1]</page>
<rawpost>fileId=[makelist.param1]&__RequestVerificationToken=$doregex[tok]</rawpost>
<referer>http://diskokosmiko.mx/[makelist.param2]</referer>
<connection>keep-alive</connection>
<accept>*/*</accept>
<X-Req>XMLHttpRequest</X-Req>
<cookieJar></cookieJar>
</regex>
<regex>
<name>tok</name>
<expres>DownloadFile.*RequestVerificationToken.*?value="([^"]+)<expres>
<page>http://diskokosmiko.mx/marcos20/peliculas-de-drama-en-espanol-latino-18845/list,1,3</page>
<referer></referer>
<connection>keep-alive</connection>
<cookieJar></cookieJar>
</regex>
<fanart>http://uscdn02.mundotkm.com/2015/12/peliculas.jpg</fanart>
<thumbnail>http://uscdn02.mundotkm.com/2015/12/peliculas.jpg</thumbnail>
</item>  
  
 
